industrial_mllm_benchmark/__init__.py
industrial_mllm_benchmark/__main__.py
industrial_mllm_benchmark/base/__init__.py
industrial_mllm_benchmark/base/base_graders.py
industrial_mllm_benchmark/base/open_ai_models.py
industrial_mllm_benchmark/base/system_prompts.py
industrial_mllm_benchmark/base/user_prompts.py
industrial_mllm_benchmark/benchmark.py
industrial_mllm_benchmark/env_yaml.py
industrial_mllm_benchmark/graders.py
industrial_mllm_benchmark/implementations.py
industrial_mllm_benchmark/models.py
industrial_mllm_benchmark/parse_context.py
industrial_mllm_benchmark/system_prompts.py
industrial_mllm_benchmark/tasks.py
industrial_mllm_benchmark/tasksets.py
industrial_mllm_benchmark-0.1.2.dist-info/LICENSE
industrial_mllm_benchmark-0.1.2.dist-info/LICENSES/LicenseRef-Datasheet.txt
industrial_mllm_benchmark-0.1.2.dist-info/LICENSES/MIT.txt
industrial_mllm_benchmark-0.1.2.dist-info/METADATA
industrial_mllm_benchmark-0.1.2.dist-info/WHEEL
industrial_mllm_benchmark-0.1.2.dist-info/entry_points.txt
industrial_mllm_benchmark-0.1.2.dist-info/RECORD
